{
	"info": {
		"_postman_id": "498420e2-5967-4756-9445-495316f2a1b1",
		"name": "Google",
		"schema": "https://schema.getpostman.com/json/collection/v2.0.0/collection.json"
	},
	"item": [
		{
			"name": "query places api",
			"request": {
				"method": "GET",
				"header": [],
				"url": {
					"raw": "https://maps.googleapis.com/maps/api/place/details/json?key=AIzaSyBTys33uJH7-oByYblJqun7EYOVldzMq5Y&placeid=ChIJ3_c1mbZ0sEcR98FkiQ6jCVo",
					"protocol": "https",
					"host": [
						"maps",
						"googleapis",
						"com"
					],
					"path": [
						"maps",
						"api",
						"place",
						"details",
						"json"
					],
					"query": [
						{
							"key": "key",
							"value": "AIzaSyBTys33uJH7-oByYblJqun7EYOVldzMq5Y"
						},
						{
							"key": "placeid",
							"value": "ChIJ3_c1mbZ0sEcR98FkiQ6jCVo"
						}
					]
				}
			},
			"response": []
		}
	],
	"protocolProfileBehavior": {}
}